LICENSE
README.md
setup.cfg
setup.py
funky_horse/__init__.py
funky_horse/random_color_palette.py
funky_horse.egg-info/PKG-INFO
funky_horse.egg-info/SOURCES.txt
funky_horse.egg-info/dependency_links.txt
funky_horse.egg-info/requires.txt
funky_horse.egg-info/top_level.txt
funky_horse/assets/accessory/bow_tie.svg
funky_horse/assets/accessory/horn1.svg
funky_horse/assets/accessory/horn2.svg
funky_horse/assets/accessory/necklace1.svg
funky_horse/assets/background/background1.svg
funky_horse/assets/body/body1.svg
funky_horse/assets/body/body2.svg
funky_horse/assets/body/body3.svg
funky_horse/assets/body/body4.svg
funky_horse/assets/ears/ears1/bg.svg
funky_horse/assets/ears/ears1/fg.svg
funky_horse/assets/eyes/eyes1.svg
funky_horse/assets/eyes/eyes2.svg
funky_horse/assets/eyes/eyes3.svg
funky_horse/assets/eyes/eyes4.svg
funky_horse/assets/eyes/eyes5.svg
funky_horse/assets/eyes/eyes6.svg
funky_horse/assets/eyes/eyes7.svg
funky_horse/assets/eyes/eyes8.svg
funky_horse/assets/eyes/eyes9.svg
funky_horse/assets/eyes/eyes_pirate_patch.svg
funky_horse/assets/eyes/eyes_zoro_mask.svg
funky_horse/assets/hair/hair1/bg.svg
funky_horse/assets/hair/hair1/fg.svg
funky_horse/assets/hair/hair2/bg.svg
funky_horse/assets/hair/hair2/fg.svg
funky_horse/assets/hair/hair3/bg.svg
funky_horse/assets/hair/hair3/fg.svg
funky_horse/assets/hair/hair4/bg.svg
funky_horse/assets/hair/hair4/fg.svg
funky_horse/assets/hair/hair5/fg.svg
funky_horse/assets/hair/hair6/bg.svg
funky_horse/assets/hair/hair6/fg.svg
funky_horse/assets/muzzle/mouth_open_1.svg
funky_horse/assets/muzzle/muzzle1.svg
funky_horse/assets/muzzle/muzzle2.svg
funky_horse/assets/muzzle/muzzle3.svg
funky_horse/assets/muzzle/muzzle4.svg
funky_horse/assets/muzzle/muzzle5.svg
funky_horse/assets/muzzle/muzzle6.svg
funky_horse/assets/muzzle/muzzle7.svg