Metadata-Version: 2.1
Name: funky-horse
Version: 1.0.4
Summary: Python-based fun avatar generator
Home-page: https://github.com/AlexandreBidon/Funky-Horse
Author: Alexandre Bidon
Author-email: alexandre.bidon.44@gmail.com
License: MIT
Download-URL: https://github.com/AlexandreBidon/Funky-Horse/archive/refs/tags/1.0.4.tar.gz
Keywords: Funky,Horse,Avatar,svg,png,Generator,Vector
Platform: UNKNOWN
Classifier: Development Status :: 3 - Alpha
Classifier: Intended Audience :: Developers
Classifier: Topic :: Software Development :: Build Tools
Classifier: License :: OSI Approved :: MIT License
Classifier: Programming Language :: Python :: 3
Classifier: Programming Language :: Python :: 3.4
Classifier: Programming Language :: Python :: 3.5
Classifier: Programming Language :: Python :: 3.6
License-File: LICENSE
